migate/__init__.py
migate/config.py
migate/passtoken.py
migate/service.py
migate/login/captcha.py
migate/login/sendcode.py
migate/login/verify.py
migate/login/verifycode.py
migate-1.0.1.dist-info/licenses/LICENSE
migate-1.0.1.dist-info/METADATA
migate-1.0.1.dist-info/WHEEL
migate-1.0.1.dist-info/top_level.txt
migate-1.0.1.dist-info/RECORD
