Metadata-Version: 2.4
Name: migate
Version: 1.0.1
Summary: migate is a simplified Xiaomi authentication gateway for Python projects
Author: offici5l
License: MIT License
Project-URL: Repository, https://github.com/offici5l/migate
Keywords: xiaomi,miunlock,MiUnlockTool,bootloader,unlock,MIUI,HyperOS,Tools,18n_bbs_global,unlockApi,xiaomiio,mi,auth,login,gateway,2fa,Captcha
Classifier: Development Status :: 5 - Production/Stable
Classifier: Programming Language :: Python :: 3
Classifier: License :: OSI Approved :: Apache Software License
Classifier: Operating System :: OS Independent
Requires-Python: >=3.7
License-File: LICENSE
Requires-Dist: requests
Requires-Dist: colorama
Dynamic: license-file
